myarduinowithpy/__init__.py
myarduinowithpy/compiler.py
myarduinowithpy/core.py
myarduinowithpy/uploader.py
myarduinowithpy/utils.py
myarduinowithpy-1.0.dist-info/METADATA
myarduinowithpy-1.0.dist-info/WHEEL
myarduinowithpy-1.0.dist-info/top_level.txt
myarduinowithpy-1.0.dist-info/RECORD
